{
  "uuid": "1e7b1f5c-8598-456f-b177-85a4d211437a",
  "platform_post_id": "1201058772237156361",
  "platform_name": "哔哩哔哩",
  "post_type": "text",
  "published_at": "2026-05-11T14:41:27+08:00",
  "source_url": "https://t.bilibili.com/1201058772237156361",
  "plain_text": "10分钟后再来玩玩竞拍之王 一千万一千万gogogo",
  "images": [],
  "stats": {
    "likes": 180,
    "comments": 8,
    "forwards": 0,
    "views": null
  },
  "is_repost": false,
  "repost": {
    "author_name": null,
    "author_url": null,
    "text": null,
    "source_url": null
  },
  "tags": [],
  "related": {
    "prev_uuid": "05a0fee6-4df3-4ac2-ad20-6c4c5e7caa83",
    "next_uuid": "0ee9361f-c881-4d26-9cd0-769448442f82"
  }
}