{
  "uuid": "2306ef65-6e51-40da-8dbf-41e6b29767c4",
  "platform_post_id": "1029213394095308803",
  "platform_name": "哔哩哔哩",
  "post_type": "repost",
  "published_at": "2025-02-02T12:33:37+08:00",
  "source_url": "https://t.bilibili.com/1029213394095308803",
  "plain_text": "也说不定哪天真会变成爱好是爬山徒步的人",
  "images": [
    {
      "filename": "1029213394095308803_100@repost.jpg",
      "width": 5120,
      "height": 2880,
      "file_size": 11438401,
      "mime_type": "image/jpeg",
      "is_cover": false,
      "is_repost_media": true
    }
  ],
  "stats": {
    "likes": 236,
    "comments": 29,
    "forwards": 0,
    "views": null
  },
  "is_repost": true,
  "repost": {
    "author_name": "岁己家的1702",
    "author_url": "https://space.bilibili.com/11308264",
    "text": null,
    "source_url": null
  },
  "tags": [],
  "related": {
    "prev_uuid": "b3cf3233-b0b1-49d5-b17b-bf180fd51e8d",
    "next_uuid": "e5f419a7-a91b-4f15-9013-ac58f7a6edb0"
  }
}